<?xml version="1.0" encoding="UTF-8" standalone="no"?>
<worldmap>
  <segment id="laeroth_caves" x="260" y="144">
    <map id="laerothcave1" x="281" y="219"/>
    <map id="laerothcave2" x="281" y="198"/>
    <map id="laerothcave3" x="275" y="177"/>
    <map id="laerothcave4" x="271" y="171"/>
    <map id="laerothtomb0" x="268" y="160"/>
    <map id="laerothtomb1" x="260" y="144"/>
  </segment>
  <segment id="island_caves" x="23" y="67">
    <map id="island_underground1" x="100" y="100"/>
    <map id="island_underground3" x="45" y="131"/>
    <map id="island_underground4" x="23" y="100"/>
    <map id="island_underground2" x="76" y="131"/>
    <map id="island_underground4a" x="47" y="67"/>
    <map id="island_underground4b" x="80" y="67"/>
    <map id="island_underground4c" x="80" y="98"/>
    <map id="island_underground5" x="59" y="104"/>
  </segment>
  <segment id="island_cave_2" x="-20" y="-43">
    <map id="island_4_cave1" x="11" y="3"/>
    <map id="island_4_cave2" x="18" y="-1"/>
    <map id="final_cave_labyrinth" x="-20" y="-16"/>
    <map id="final_cave1" x="-19" y="-47"/>
  </segment>
  <segment id="laeroth_prison" x="50" y="50">
    <map id="laerothprison2" x="50" y="50"/>
    <map id="laerothprison3" x="65" y="50"/>
    <map id="laerothprison4" x="65" y="63"/>
    <map id="laerothprison5" x="68" y="77"/>
    <map id="laerothprison6" x="99" y="94"/>
    <map id="laerothprison7" x="99" y="63"/>
  </segment>
</worldmap>
